{
  "version": 1,
  "functions": {
    "/api/bases-pago/borrar-todo": {},
    "/api/asesor/casos": {},
    "/api/asesor/casos/debug": {},
    "/api/asesor/casos/[numero_prestamo]": {},
    "/api/collection/casos/[numero_prestamo]": {},
    "/api/bases-pago/borrar/[id]": {},
    "/api/bases-pago/listar": {},
    "/api/asesor/casos/[numero_prestamo]/generar-liga": {},
    "/api/auth/login-asesor": {},
    "/api/cliente/probe": {},
    "/api/bases-pago/ver/[id]": {},
    "/api/collection/casos/[numero_prestamo]/generar-liga": {},
    "/api/collection/aplicaciones/[listKey]": {},
    "/api/collection/assignable-users": {},
    "/api/collection/casos/reset-assign": {},
    "/api/collection/casos/auto-assign": {},
    "/api/collection/casos/resegment": {},
    "/api/db-info": {},
    "/api/dev/set-asesor": {},
    "/api/collection/casos/wipe": {},
    "/api/collection/casos": {},
    "/api/listas/[id]/items/tipo/[tipo]/lista/[listaNombre]": {},
    "/api/listas/[id]": {},
    "/api/listas/by-tipo/[tipo]/items": {},
    "/api/collection/casos/import": {},
    "/api/listas/items/tipo/[tipo]": {},
    "/api/listas": {},
    "/api/login": {},
    "/api/listas/tipo/[tipo]": {},
    "/api/otp/verify": {},
    "/api/otp/send": {},
    "/api/plantillas-complejas/[id]": {},
    "/api/plantillas-personalizadas/[id]": {},
    "/api/plantillas-complejas": {},
    "/api/plantillas-temporales-2/config": {},
    "/api/plantillas-temporales-3/config": {},
    "/api/plantillas-complejas/config": {},
    "/api/plantillas-temporales-2/[token]": {},
    "/api/plantillas-temporales-2": {},
    "/api/plantillas-temporales-3/[token]": {},
    "/api/plantillas-personalizadas/config": {},
    "/api/plantillas-personalizadas": {},
    "/api/plantillas-temporales/[token]": {},
    "/api/plantillas-temporales/config": {},
    "/api/plantillas/[id]/listas/[tipo]": {},
    "/api/plantillas-temporales": {},
    "/api/plantillas/[id]": {},
    "/api/reportes/download": {},
    "/api/plantillas": {},
    "/api/plantillas/visual": {},
    "/api/reportes/list": {},
    "/api/reportes/cron": {},
    "/api/reportes/manual": {},
    "/api/reportes/generar": {},
    "/api/plantillas-temporales-3": {},
    "/api/reportes/schedule": {},
    "/api/sync-pago/[token]": {},
    "/api/sync-pago": {},
    "/enlace-temporal/[token]": {}
  }
}